{"cameraMode":{"drawMode":0,"name":"Shaded","section":"Shading Mode"},"sceneLighting":true,"audioPlay":false,"sceneViewState":{"m_AlwaysRefresh":false,"showFog":true,"showSkybox":true,"showFlares":true,"showImageEffects":true,"showParticleSystems":true,"showVisualEffectGraphs":true,"m_FxEnabled":true},"in2DMode":false,"pivot":{"x":18.278745651245118,"y":6.744654655456543,"z":4.285077095031738},"rotation":{"x":-0.35640352964401247,"y":-0.042577169835567477,"z":0.01625225320458412,"w":-0.9332297444343567},"size":10.218624114990235,"orthographic":false}